Workbook

Sheet Instrucciones
A1: Planilla de levantamiento · Cocina central Grupo BS 2000
A2: Fase 0 · 26-10-2026 · Acompaña a entregables/00-fase-0-levantamiento-de-datos.md
A4: Cómo usar esta planilla
A5: 1. Llena solo las celdas AMARILLAS. Lo demás lo preparó el equipo consultor.
A6: 2. La fila GRIS en itálica de cada tabla es un EJEMPLO del formato esperado. No la borres; no se toma en cuenta.
A7: 3. Empieza por las filas P1 (bloqueantes). Con el bloque P1 completo arranca la Fase 1.
A8: 4. Medidas en metros con 2 decimales (ej. 7,52) o en cm donde lo indica el encabezado.
A9: 5. Nombra las fotos con el código de la fila (ej. P1-09_campana_frente.jpg) y súbelas a insumos/fotos/.
A10: 6. Cuando termines un dato, cambia el Estado a «Listo» en la hoja 1-Checklist.
A11: 7. Seguridad: no abras tableros eléctricos ni manipules el gas. Para eso, mantenimiento o un electricista.
A13: Leyenda
B14: Celda para llenar
B15: Fila de ejemplo
B16: P1 · Bloqueante
B17: P2 · Programa y layout
B18: P3 · Ingeniería, obra y presupuesto
A20: Hojas
A21: 1-Checklist | B21: Todos los datos, uno por fila, con su prioridad y estado
A22: 2-Tramos y alturas | B22: P1-04 y P1-05: tramos de pared, diagonales y alturas libres
A23: 3-Columnas | B23: P1-06: ubicación y sección de cada columna
A24: 4-Puertas y vanos | B24: P1-07: puertas, incluidas las de cavas
A25: 5-Cavas | B25: P2-07: uso, temperatura, medidas y puerta de cada cava
A26: 6-Equipos existentes | B26: P2-08: inventario con placa, medidas, energía, estado y decisión
A28: Avance (se calcula solo con la columna Estado de 1-Checklist)
A29: Prioridad | B29: Total de datos | C29: Listos o No aplica | D29: Pendientes o En proceso | E29: % de avance
A30: P1 · Bloqueante | B30: =COUNTIFS('1-Checklist'!$B$6:$B$85,"P1") -> 36 | C30: =COUNTIFS('1-Checklist'!$B$6:$B$85,"P1",'1-Checklist'!$K$6:$K$85,"Listo")+COUNTIFS('1-Checklist'!$B$6:$B$85,"P1",'1-Checklist'!$K$6:$K$85,"No aplica") -> 0 | D30: =B30-C30 -> 36 | E30: =IF(B30=0,0,C30/B30) -> 0
A31: P2 · Programa y layout | B31: =COUNTIFS('1-Checklist'!$B$6:$B$85,"P2") -> 30 | C31: =COUNTIFS('1-Checklist'!$B$6:$B$85,"P2",'1-Checklist'!$K$6:$K$85,"Listo")+COUNTIFS('1-Checklist'!$B$6:$B$85,"P2",'1-Checklist'!$K$6:$K$85,"No aplica") -> 0 | D31: =B31-C31 -> 30 | E31: =IF(B31=0,0,C31/B31) -> 0
A32: P3 · Ingeniería, obra y presupuesto | B32: =COUNTIFS('1-Checklist'!$B$6:$B$85,"P3") -> 14 | C32: =COUNTIFS('1-Checklist'!$B$6:$B$85,"P3",'1-Checklist'!$K$6:$K$85,"Listo")+COUNTIFS('1-Checklist'!$B$6:$B$85,"P3",'1-Checklist'!$K$6:$K$85,"No aplica") -> 0 | D32: =B32-C32 -> 14 | E32: =IF(B32=0,0,C32/B32) -> 0
A33: Total | B33: =SUM(B30:B32) -> 80 | C33: =SUM(C30:C32) -> 0 | D33: =SUM(D30:D32) -> 80 | E33: =IF(B33=0,0,C33/B33) -> 0

Sheet 1-Checklist
A1: Checklist de levantamiento · Fase 0
A2: Llena solo las celdas amarillas. La fila gris es un ejemplo. Los códigos coinciden con entregables/00-fase-0-levantamiento-de-datos.md.
A4: ID | B4: Prioridad | C4: Disciplina | D4: Dato requerido | E4: Cómo obtenerlo | F4: Unidad / formato | G4: Valor o respuesta | H4: Foto(s): nombre de archivo | I4: Responsable | J4: Fecha | K4: Estado | L4: Observaciones
A5: EJEMPLO | B5: P1 | C5: Arquitectura | D5: Muro hacia el restaurante: espesor | E5: Medir en el marco de la puerta de servicio | F5: cm | G5: 15 | H5: P1-08_muro_marco.jpg | I5: Pedro (mantenimiento) | J5: 28/10/2026 | K5: Listo | L5: Bloque frisado por ambas caras
A6: P1-01a | B6: P1 | C6: General | D6: Plano de planta baja subido a insumos/ | E6: Subir plano-planta-baja.png (ver insumos/README.md) | F6: Archivo | K6: Pendiente
A7: P1-01b | B7: P1 | C7: General | D7: Fotos actuales subidas a insumos/fotos/: cocina, pisos, paredes, techo, campana, cavas, equipos | E7: Lista mínima en insumos/README.md | F7: Archivos | K7: Pendiente
A8: P1-01c | B8: P1 | C8: General | D8: Captura(s) del listado de equipos a comprar subida(s) | E8: Subir equipos-a-comprar.png | F8: Archivo | K8: Pendiente
A9: P1-02 | B9: P1 | C9: Equipos | D9: ¿Ya compraste o pagaste algún equipo de la lista? ¿Cuáles? | E9: Respuesta directa. Recomendación: no comprar aún los equipos a gas ni el iVario | F9: Texto | K9: Pendiente
A10: P1-03a | B10: P1 | C10: Legal / hotel | D10: Obras que permite el contrato: abrir muro al restaurante, piso, desagües, campana, acometidas | E10: Revisar contrato de arrendamiento | F10: Texto | K10: Pendiente
A11: P1-03b | B11: P1 | C11: Legal / hotel | D11: Quién aprueba la obra en el hotel y en qué plazo | E11: Conversación con el hotel | F11: Texto | K11: Pendiente
A12: P1-04 | B12: P1 | C12: Arquitectura | D12: Medidas del polígono: tramos de pared y diagonales | E12: Protocolo §6.2. Anotar en la hoja 2 | F12: m (2 decimales) | K12: Pendiente
A13: P1-05 | B13: P1 | C13: Arquitectura | D13: Alturas libres h1–h4 en al menos 4 puntos | E13: Protocolo §6.3. Anotar en la hoja 2 | F13: m | K13: Pendiente
A14: P1-06 | B14: P1 | C14: Arquitectura | D14: Columnas: ubicación y sección (sobre todo la que está bajo la campana) | E14: Protocolo §6.4. Anotar en la hoja 3 | F14: m / cm | K14: Pendiente
A15: P1-07 | B15: P1 | C15: Arquitectura | D15: Puertas y vanos, incluidas las puertas de cavas | E15: Protocolo §6.5. Anotar en la hoja 4 | F15: cm | K15: Pendiente
A16: P1-08a | B16: P1 | C16: Arquitectura | D16: Muro hacia el restaurante: material | E16: Golpear: ¿hueco o macizo? Protocolo §6.6 | F16: Bloque / concreto / drywall / otro | K16: Pendiente
A17: P1-08b | B17: P1 | C17: Arquitectura | D17: Muro hacia el restaurante: espesor | E17: Medir en el marco de la puerta de servicio | F17: cm | K17: Pendiente
... A85: P3-10 | B85: P3 | C85: Presupuesto | D85: Proveedores locales de confianza: contratistas, electricistas, acero inoxidable, distribuidores | E85: Lista con contacto | F85: Texto | K85: Pendiente

Sheet 2-Tramos y alturas
A1: Tramos, diagonales y alturas libres (P1-04, P1-05)
A2: Esquina A = puerta de mercancía; sigue en sentido horario. Mide a 1 m de altura, de pared a pared, en metros con 2 decimales.
A4: Tramos de pared
A5: Tramo | B5: Orientación (N / S / E / O) | C5: Largo (m) | D5: Revestimiento actual | E5: Estado | F5: Foto | G5: Notas
A6: EJEMPLO · A–B | B6: N | C6: 7.52 | D6: Cerámica blanca | E6: Regular, juntas abiertas | F6: P1-04_A-B.jpg | G6: Puerta de servicio al restaurante a 2,10 m de A
A7: A–B
A8: B–C
A9: C–D
A10: D–E
A11: E–F
A12: F–G
A13: G–H
A14: H–I
A15: I–J
A16: J–K
A17: K–L
A18: L–M
... A21: O–P
B25: Perímetro medido (m) | C25: =SUM(C7:C24) -> 0
B26: Las filas sin uso se dejan vacías. Si hay más de 18 tramos, inserta filas dentro de la tabla.
A28: Diagonales (comprobación de escuadra)
A29: Rectángulo / zona | B29: Diagonal 1 (de → a) | C29: Largo diag. 1 (m) | D29: Diagonal 2 (de → a) | E29: Largo diag. 2 (m) | F29: Diferencia (m) | G29: Notas
A30: EJEMPLO · Ala principal | B30: A → D | C30: 21.35 | D30: B → C | E30: 21.31 | F30: =IF(OR(C30="",E30=""),"",ABS(C30-E30)) -> 0.04 | G30: Diferencia < 5 cm = a escuadra
F31: =IF(OR(C31="",E31=""),"",ABS(C31-E31))
F32: =IF(OR(C32="",E32=""),"",ABS(C32-E32))
F33: =IF(OR(C33="",E33=""),"",ABS(C33-E33))
F34: =IF(OR(C34="",E34=""),"",ABS(C34-E34))
A37: Alturas libres (ver diagrama en §6.3)
A38: Punto de medición | B38: h1 piso → placa (m) | C38: h2 piso → fondo de viga (m) | D38: h3 piso → ducto / tubería más baja (m) | E38: h4 piso → borde inferior campana (m) | F38: Foto | G38: Notas
A39: EJEMPLO · Junto a la campana | B39: 3.4 | C39: 3.05 | D39: 2.7 | E39: 2.05 | F39: P1-05_campana.jpg | G39: Ducto de inyección a 2,70 m
A40: Junto a la campana
A41: Centro del ala Blue58
A42: Zona de producción
A43: Entrada de mercancía
A46: Altura libre mínima medida (m) | D46: =IF(COUNT(B40:D45)=0,"",MIN(B40:D45))

Sheet 3-Columnas
A1: Columnas (P1-06)
A2: Numera las columnas en el croquis (C1, C2…). Mide la distancia a dos paredes perpendiculares y la sección.
A4: ID | B4: Ubicación (descripción) | C4: Pared de referencia 1 | D4: Distancia a pared 1 (m) | E4: Pared de referencia 2 | F4: Distancia a pared 2 (m) | G4: Sección ancho × fondo (cm) o diámetro | H4: ¿Bajo la campana? | I4: Foto | J4: Notas
A5: EJEMPLO | B5: Bajo la campana central | C5: Tramo A–B (norte) | D5: 3.2 | E5: Tramo D–E (este) | F5: 8.45 | G5: 40 × 40 | H5: Sí | I5: P1-06_C1.jpg | J5: Revestida en cerámica
A6: C1
A7: C2
A8: C3
A9: C4
A10: C5
A11: C6
A12: C7
A13: C8

Sheet 4-Puertas y vanos
A1: Puertas y vanos (P1-07)
A2: Incluye las puertas de todas las cavas. Ancho libre de marco a marco, por dentro.
A4: ID | B4: Conecta la cocina con… | C4: Tramo donde está | D4: Ancho libre (cm) | E4: Alto libre (cm) | F4: Tipo | G4: Abre hacia | H4: ¿Pasan carros hoy? | I4: Foto | J4: Notas
A5: EJEMPLO | B5: Restaurante (puerta de servicio) | C5: A–B | D5: 90 | E5: 210 | F5: Vaivén | G5: Ambos lados | H5: No | I5: P1-07_PU1.jpg | J5: Sin visor; choques frecuentes
A6: PU1 | B6: Restaurante (puerta de servicio)
A7: PU2 | B7: Salón Privado 1
A8: PU3 | B8: Entrada de mercancía
A9: PU4 | B9: Salida de catering
A10: PU5 | B10: Escalera de servicio / almacén
A11: PU6 | B11: Cava de vegetales
A12: PU7 | B12: Cava de congelación
A13: PU8 | B13: Cava de conservación sur 1
A14: PU9 | B14: Cava de conservación sur 2
A15: PU10 | B15: Cava de conservación sur 3
A16: PU11 | B16: Área climatizada de pasapalos
A17: PU12 | B17: Almacén de cristalería

Sheet 5-Cavas
A1: Cavas (P2-07)
A2: Las cavas son fijas e inamovibles. Agrega filas si hay más cavas de conservación al sur.
A4: ID | B4: Nombre / uso actual | C4: Ubicación | D4: Temperatura de trabajo (°C) | E4: Medidas internas L × A × H (m) | F4: Puerta: ancho (cm) | G4: Puerta: abre hacia | H4: Condensador: ubicación | I4: Estado | J4: ¿En planta eléctrica? | K4: Foto | L4: Notas
A5: EJEMPLO | B5: Cava de vegetales | C5: Extremo este, dentro del polígono | D5: 4 | E5: 3,00 × 2,40 × 2,40 | F5: 80 | G5: Hacia la cocina | H5: Azotea | I5: Bueno | J5: Sí | K5: P2-07_CV1.jpg | L5: Empaque de puerta gastado
A6: CV1 | B6: Cava de vegetales | C6: Extremo este, dentro del polígono
A7: CV2 | B7: Cava de congelación | C7: Oeste
A8: CV3 | B8: Cava de conservación 1 | C8: Sur
A9: CV4 | B9: Cava de conservación 2 | C9: Sur
A10: CV5 | B10: Cava de conservación 3 | C10: Sur
A11: CV6 | B11: Cava de conservación 4 | C11: Sur

Sheet 6-Equipos existentes
A1: Inventario de equipos existentes (P2-08)
A2: Por equipo: foto de frente con la cinta métrica y foto de la placa de datos. La lista viene del encargo; corrige o agrega lo que falte.
A4: ID | B4: Equipo | C4: Cantidad | D4: Marca | E4: Modelo | F4: Ancho (cm) | G4: Fondo (cm) | H4: Alto (cm) | I4: Energía | J4: Voltaje (V) | K4: Fases | L4: Amperios (A) o kW | M4: BTU/h (si es a gas) | N4: ¿Agua? | O4: ¿Desagüe? | P4: Estado | Q4: Decisión | R4: Ubicación actual | S4: Foto placa | T4: Foto frontal | U4: Notas
A5: EJEMPLO | B5: Horno de convección a gas #1 (sobre base-rack) | C5: 1 | D5: Vulcan | E5: VC4GD | F5: 102 | G5: 104 | H5: 140 | I5: GLP | J5: 120 | K5: 1 | L5: 6 A | M5: 50000 | N5: No | O5: No | P5: Regular | Q5: Se queda | R5: Junto a la campana, lado sur | S5: P2-08_EX07_placa.jpg | T5: P2-08_EX07_frente.jpg | U5: Puerta cierra mal
A6: EX01 | B6: Cocina de 6 hornillas con horno
A7: EX02 | B7: Hornillas sueltas
A8: EX03 | B8: Plancha(s) a gas
A9: EX04 | B9: Parrilla tipo charbroiler
A10: EX05 | B10: Baño de María de 2 pozos
A11: EX06 | B11: Freidora(s)
A12: EX07 | B12: Horno de convección Vulcan a gas #1 (sobre base-rack)
A13: EX08 | B13: Horno de convección Vulcan a gas #2 (sobre base-rack)
A14: EX09 | B14: Horno combi (por confirmar marca y modelo)
A15: EX10 | B15: Mesa(s) refrigerada(s) bajo mesón
A16: EX11 | B16: Refrigerador True 2 puertas ("cava de pescados")
A17: EX12 | B17: Refrigerador True 2 puertas ("cava de transición/pescados")
... A28: EX23 | B28: Lámparas fluorescentes estancas
A29: EX24
A30: EX25
A31: EX26
A32: EX27
A33: EX28
A34: EX29
A35: EX30
A36: EX31
